TracAttachmentNumMacro-0.8.dist-info/METADATA
TracAttachmentNumMacro-0.8.dist-info/RECORD
TracAttachmentNumMacro-0.8.dist-info/WHEEL
TracAttachmentNumMacro-0.8.dist-info/entry_points.txt
TracAttachmentNumMacro-0.8.dist-info/top_level.txt
tracattachmentnum/__init__.py
tracattachmentnum/attachmentnum.py
